reposync/__init__.py
reposync/cli/__init__.py
reposync/git.py
reposync/parser.py
reposync/reposync.py
reposync/tree.py
reposync-0.8.0.dist-info/entry_points.txt
reposync-0.8.0.dist-info/LICENSE
reposync-0.8.0.dist-info/WHEEL
reposync-0.8.0.dist-info/METADATA
reposync-0.8.0.dist-info/RECORD
