Metadata-Version: 2.1
Name: reposync
Version: 0.8.0
Summary: Organize git repositories.
Home-page: http://github.com/devinalvaro/reposync
License: MIT
Author: Devin Alvaro
Author-email: devin.alvaro@gmail.com
Requires-Python: >=3.7,<4.0
Classifier: Environment :: Console
Classifier: Intended Audience :: Developers
Classifier: License :: OSI Approved :: MIT License
Classifier: Programming Language :: Python :: 3
Classifier: Programming Language :: Python :: 3.7
Classifier: Programming Language :: Python :: 3.8
Classifier: Topic :: Software Development :: Version Control :: Git
Requires-Dist: fire (>=0.2.1,<0.3.0)
Requires-Dist: gitpython (>=3.0.5,<4.0.0)
Requires-Dist: pyaml (>=19.12.0,<20.0.0)
Project-URL: Repository, http://github.com/devinalvaro/reposync
